client/__init__.py
client/dataset.py
client/mountain.py
client/project.py
client/team.py
mountain_ai_py-0.0.2.dist-info/LICENSE
mountain_ai_py-0.0.2.dist-info/METADATA
mountain_ai_py-0.0.2.dist-info/WHEEL
mountain_ai_py-0.0.2.dist-info/top_level.txt
mountain_ai_py-0.0.2.dist-info/RECORD
